sqlite_utils_sqlite_html/__init__.py
sqlite_utils_sqlite_html/version.py
sqlite_utils_sqlite_html-0.1.3.dist-info/METADATA
sqlite_utils_sqlite_html-0.1.3.dist-info/WHEEL
sqlite_utils_sqlite_html-0.1.3.dist-info/entry_points.txt
sqlite_utils_sqlite_html-0.1.3.dist-info/top_level.txt
sqlite_utils_sqlite_html-0.1.3.dist-info/RECORD
