Metadata-Version: 2.1
Name: sqlite-utils-sqlite-html
Version: 0.1.3
Summary: TODO
Author: Alex Garcia
License: Apache-2.0
Project-URL: Homepage, https://github.com/asg017/sqlite-html
Project-URL: Changelog, https://github.com/asg017/sqlite-html/releases
Project-URL: Issues, https://github.com/asg017/sqlite-html/issues
Requires-Dist: sqlite-utils
Requires-Dist: sqlite-html
